.version
MANIFEST.in
README.rst
setup.cfg
setup.py
media_converter/__init__.py
media_converter/codecs.py
media_converter/media_converter.py
media_converter/tracks.py
media_converter.egg-info/PKG-INFO
media_converter.egg-info/SOURCES.txt
media_converter.egg-info/dependency_links.txt
media_converter.egg-info/not-zip-safe
media_converter.egg-info/requires.txt
media_converter.egg-info/top_level.txt
media_converter/streams/__init__.py
media_converter/streams/instream.py
media_converter/streams/outstream.py