Metadata-Version: 1.0
Name: media-converter
Version: 1.1.2
Summary: Media Converter
Home-page: https://github.com/smartstudy/media_converter
Author: DevOps Team, SMARTSTUDY
Author-email: d9@smartstudy.co.kr
License: UNKNOWN
Platform: UNKNOWN
